genv/__init__.py
genv/_ray/__init__.py
genv/_ray/remote.py
genv/cli/__init__.py
genv/cli/__main__.py
genv/cli/activate.py
genv/cli/attach.py
genv/cli/config.py
genv/cli/deactivate.py
genv/cli/detach.py
genv/cli/devices.py
genv/cli/enforce.py
genv/cli/envs.py
genv/cli/home.py
genv/cli/llm.py
genv/cli/lock.py
genv/cli/monitor.py
genv/cli/remote.py
genv/cli/shell.py
genv/cli/status.py
genv/cli/usage.py
genv/cli/version.py
genv/core/__init__.py
genv/core/devices.py
genv/core/envs.py
genv/core/processes.py
genv/core/snapshot.py
genv/core/system.py
genv/core/utils.py
genv/enforce/__init__.py
genv/enforce/execute.py
genv/enforce/rules/__init__.py
genv/enforce/rules/env_devices.py
genv/enforce/rules/env_memory.py
genv/enforce/rules/max_devices_per_user.py
genv/enforce/rules/non_env_processes.py
genv/entities/__init__.py
genv/entities/core/__init__.py
genv/entities/core/devices.py
genv/entities/core/envs.py
genv/entities/core/processes.py
genv/entities/core/snapshot.py
genv/entities/core/system.py
genv/entities/enforce/__init__.py
genv/entities/enforce/report.py
genv/entities/enforce/survey.py
genv/metrics/__init__.py
genv/metrics/collection.py
genv/metrics/metric.py
genv/metrics/publisher.py
genv/metrics/spec.py
genv/metrics/specs.py
genv/metrics/type.py
genv/metrics/export/grafana/grafana.ini
genv/metrics/export/grafana/dashboards/overview.json
genv/metrics/export/grafana/provisioning/dashboards/default.yml
genv/metrics/export/grafana/provisioning/datasources/default.yml
genv/metrics/export/prometheus/prometheus.yml
genv/ray/__init__.py
genv/remote/__init__.py
genv/remote/core/__init__.py
genv/remote/core/devices.py
genv/remote/core/envs.py
genv/remote/core/processes.py
genv/remote/core/snapshot.py
genv/remote/core/system.py
genv/remote/enforce/__init__.py
genv/remote/enforce/execute.py
genv/remote/metrics/__init__.py
genv/remote/metrics/collection.py
genv/remote/utils/__init__.py
genv-1.4.3.dist-info/METADATA
genv-1.4.3.dist-info/RECORD
genv-1.4.3.dist-info/WHEEL
genv-1.4.3.dist-info/entry_points.txt
genv-1.4.3.dist-info/top_level.txt
