Metadata-Version: 2.1
Name: genv
Version: 1.4.3
Summary: GPU environment and cluster management
Home-page: https://github.com/run-ai/genv
Author: Run.ai
Author-email: pypi@run.ai
Classifier: Development Status :: 5 - Production/Stable
Classifier: Environment :: Console
Classifier: Environment :: GPU
Classifier: License :: OSI Approved :: GNU Affero General Public License v3 or later (AGPLv3+)
Classifier: Programming Language :: Python
Classifier: Programming Language :: Python :: 3
Classifier: Topic :: System :: Shells
Classifier: Topic :: Terminals
Requires-Python: >=3.7
Provides-Extra: admin
Provides-Extra: dev
Provides-Extra: monitor
Provides-Extra: ray
License-File: LICENSE
Requires-Dist: psutil
Provides-Extra: admin
Requires-Dist: prometheus-client; extra == 'admin'
Provides-Extra: dev
Requires-Dist: black; extra == 'dev'
Provides-Extra: monitor
Requires-Dist: prometheus-client; extra == 'monitor'
Provides-Extra: ray
Requires-Dist: ray; extra == 'ray'
Requires-Dist: pynvml; extra == 'ray'
